{
  "default_localization": "en",
  "dependencies": [
    {
      "file_system": null,
      "identity": "swift-syntax",
      "name": "swift-syntax",
      "source_control": null
    },
    {
      "file_system": null,
      "identity": "xctest-dynamic-overlay",
      "name": "xctest-dynamic-overlay",
      "source_control": null
    },
    {
      "file_system": null,
      "identity": "swift-docc-plugin",
      "name": "swift-docc-plugin",
      "source_control": null
    },
    {
      "file_system": null,
      "identity": "swift-macro-testing",
      "name": "swift-macro-testing",
      "source_control": null
    }
  ],
  "name": "swift-case-paths",
  "path": "/private/var/tmp/_bazel_adincebic/d542141b6540f70d4755466fcd988e58/external/rules_swift_package_manager~~swift_deps~swiftpkg_swift_case_paths",
  "platforms": [
    {
      "name": "ios",
      "version": "13.0"
    },
    {
      "name": "macos",
      "version": "10.15"
    },
    {
      "name": "tvos",
      "version": "13.0"
    },
    {
      "name": "watchos",
      "version": "6.0"
    }
  ],
  "products": [
    {
      "name": "CasePaths",
      "targets": [
        "CasePaths"
      ],
      "type": {
        "executable": false,
        "is_executable": false,
        "is_library": true,
        "is_macro": false,
        "is_plugin": false,
        "library": {
          "kind": "automatic"
        }
      }
    }
  ],
  "targets": [
    {
      "artifact_download_info": null,
      "c99name": "CasePaths",
      "clang_settings": null,
      "clang_src_info": null,
      "cxx_settings": null,
      "dependencies": [
        {
          "by_name": {
            "condition": null,
            "name": "CasePathsMacros"
          },
          "product": null,
          "target": null
        },
        {
          "by_name": null,
          "product": {
            "condition": null,
            "dep_name": "xctest-dynamic-overlay",
            "product_name": "IssueReporting"
          },
          "target": null
        },
        {
          "by_name": null,
          "product": {
            "condition": null,
            "dep_name": "xctest-dynamic-overlay",
            "product_name": "XCTestDynamicOverlay"
          },
          "target": null
        }
      ],
      "exclude_paths": [],
      "label": {
        "name": "CasePaths.rspm",
        "package": "",
        "repository_name": "@"
      },
      "linker_settings": null,
      "module_type": "SwiftTarget",
      "name": "CasePaths",
      "objc_src_info": null,
      "path": "Sources/CasePaths",
      "product_memberships": [
        "CasePaths"
      ],
      "public_hdrs_path": null,
      "resources": [],
      "source_paths": null,
      "sources": [
        "AnyCasePath.swift",
        "CasePathIterable.swift",
        "CasePathReflectable.swift",
        "CasePathable.swift",
        "EnumReflection.swift",
        "Internal/Deprecations.swift",
        "Internal/LockIsolated.swift",
        "Internal/OpenExistential.swift",
        "Internal/TypeName.swift",
        "Internal/UncheckedSendable.swift",
        "Macros.swift",
        "Never+CasePathable.swift",
        "Optional+CasePathable.swift",
        "Result+CasePathable.swift",
        "XCTestSupport.swift"
      ],
      "swift_settings": null,
      "swift_src_info": {
        "discovered_res_files": [],
        "has_objc_directive": false
      },
      "type": "regular"
    },
    {
      "artifact_download_info": null,
      "c99name": "CasePathsTests",
      "clang_settings": null,
      "clang_src_info": null,
      "cxx_settings": null,
      "dependencies": [
        {
          "by_name": {
            "condition": null,
            "name": "CasePaths"
          },
          "product": null,
          "target": null
        }
      ],
      "exclude_paths": [],
      "label": {
        "name": "CasePathsTests.rspm",
        "package": "",
        "repository_name": "@"
      },
      "linker_settings": null,
      "module_type": "SwiftTarget",
      "name": "CasePathsTests",
      "objc_src_info": null,
      "path": "Tests/CasePathsTests",
      "product_memberships": [],
      "public_hdrs_path": null,
      "resources": [],
      "source_paths": null,
      "sources": [
        "CasePathableTests.swift",
        "CasePathsTests.swift",
        "CaseSetTests.swift",
        "DeprecatedTests.swift",
        "DeprecatedXCTModifyTests.swift",
        "MacroTests.swift",
        "ReflectionTests.swift",
        "XCTModifyTests.swift",
        "XCTUnwrapTests.swift"
      ],
      "swift_settings": null,
      "swift_src_info": {
        "discovered_res_files": [],
        "has_objc_directive": false
      },
      "type": "test"
    },
    {
      "artifact_download_info": null,
      "c99name": "CasePathsMacros",
      "clang_settings": null,
      "clang_src_info": null,
      "cxx_settings": null,
      "dependencies": [
        {
          "by_name": null,
          "product": {
            "condition": null,
            "dep_name": "swift-syntax",
            "product_name": "SwiftSyntaxMacros"
          },
          "target": null
        },
        {
          "by_name": null,
          "product": {
            "condition": null,
            "dep_name": "swift-syntax",
            "product_name": "SwiftCompilerPlugin"
          },
          "target": null
        }
      ],
      "exclude_paths": [],
      "label": {
        "name": "CasePathsMacros.rspm",
        "package": "",
        "repository_name": "@"
      },
      "linker_settings": null,
      "module_type": "SwiftTarget",
      "name": "CasePathsMacros",
      "objc_src_info": null,
      "path": "Sources/CasePathsMacros",
      "product_memberships": [
        "CasePaths"
      ],
      "public_hdrs_path": null,
      "resources": [],
      "source_paths": null,
      "sources": [
        "CasePathableMacro.swift",
        "Plugin.swift"
      ],
      "swift_settings": null,
      "swift_src_info": {
        "discovered_res_files": [],
        "has_objc_directive": false
      },
      "type": "macro"
    },
    {
      "artifact_download_info": null,
      "c99name": "CasePathsMacrosTests",
      "clang_settings": null,
      "clang_src_info": null,
      "cxx_settings": null,
      "dependencies": [
        {
          "by_name": {
            "condition": null,
            "name": "CasePathsMacros"
          },
          "product": null,
          "target": null
        },
        {
          "by_name": null,
          "product": {
            "condition": null,
            "dep_name": "swift-macro-testing",
            "product_name": "MacroTesting"
          },
          "target": null
        }
      ],
      "exclude_paths": [],
      "label": {
        "name": "CasePathsMacrosTests.rspm",
        "package": "",
        "repository_name": "@"
      },
      "linker_settings": null,
      "module_type": "SwiftTarget",
      "name": "CasePathsMacrosTests",
      "objc_src_info": null,
      "path": "Tests/CasePathsMacrosTests",
      "product_memberships": [],
      "public_hdrs_path": null,
      "resources": [],
      "source_paths": null,
      "sources": [
        "CasePathableMacroTests.swift"
      ],
      "swift_settings": null,
      "swift_src_info": {
        "discovered_res_files": [],
        "has_objc_directive": false
      },
      "type": "test"
    }
  ],
  "tools_version": "6.0.0",
  "url": "https://github.com/pointfreeco/swift-case-paths",
  "version": "1.5.6"
}